BoatBuddy/.DS_Store
BoatBuddy/__init__.py
BoatBuddy/__main__.py
BoatBuddy/clock_plugin.py
BoatBuddy/console_manager.py
BoatBuddy/database_manager.py
BoatBuddy/email_manager.py
BoatBuddy/flask_manager.py
BoatBuddy/generic_plugin.py
BoatBuddy/globals.py
BoatBuddy/gps_plugin.py
BoatBuddy/log_manager.py
BoatBuddy/mysql_wrapper.py
BoatBuddy/nmea_plugin.py
BoatBuddy/notifications_manager.py
BoatBuddy/plugin_manager.py
BoatBuddy/sample-config.json
BoatBuddy/sound_manager.py
BoatBuddy/utils.py
BoatBuddy/victron_plugin.py
BoatBuddy/resources/.DS_Store
BoatBuddy/resources/alarm.mp3
BoatBuddy/resources/application_started.mp3
BoatBuddy/resources/session_ended.wav
BoatBuddy/resources/session_started.mp3
BoatBuddy/resources/warning.mp3
BoatBuddy/static/.DS_Store
BoatBuddy/static/favicon.ico
BoatBuddy/static/gauge.min.js
BoatBuddy/static/jquery-3.6.0.js
BoatBuddy/static/logo.png
BoatBuddy/static/main.css
BoatBuddy/static/popper.min.js
BoatBuddy/static/popper.min.js.map
BoatBuddy/static/bootstrap/.DS_Store
BoatBuddy/static/bootstrap/css/bootstrap-grid.css
BoatBuddy/static/bootstrap/css/bootstrap-grid.css.map
BoatBuddy/static/bootstrap/css/bootstrap-grid.min.css
BoatBuddy/static/bootstrap/css/bootstrap-grid.min.css.map
BoatBuddy/static/bootstrap/css/bootstrap-grid.rtl.css
BoatBuddy/static/bootstrap/css/bootstrap-grid.rtl.css.map
BoatBuddy/static/bootstrap/css/bootstrap-grid.rtl.min.css
BoatBuddy/static/bootstrap/css/bootstrap-grid.rtl.min.css.map
BoatBuddy/static/bootstrap/css/bootstrap-reboot.css
BoatBuddy/static/bootstrap/css/bootstrap-reboot.css.map
BoatBuddy/static/bootstrap/css/bootstrap-reboot.min.css
BoatBuddy/static/bootstrap/css/bootstrap-reboot.min.css.map
BoatBuddy/static/bootstrap/css/bootstrap-reboot.rtl.css
BoatBuddy/static/bootstrap/css/bootstrap-reboot.rtl.css.map
BoatBuddy/static/bootstrap/css/bootstrap-reboot.rtl.min.css
BoatBuddy/static/bootstrap/css/bootstrap-reboot.rtl.min.css.map
BoatBuddy/static/bootstrap/css/bootstrap-utilities.css
boatbuddy-0.7.0.dist-info/METADATA
boatbuddy-0.7.0.dist-info/WHEEL
boatbuddy-0.7.0.dist-info/licenses/LICENSE
boatbuddy-0.7.0.dist-info/RECORD
