Metadata-Version: 2.1
Name: BoatBuddy
Version: 0.7.0
Summary: A suite of tools to help collecting NMEA0183 and other marine metrics in a digital logbook format
Project-URL: Homepage, https://joezeitouny.github.io/bb/
Project-URL: Bug Tracker, https://github.com/joezeitouny/BoatBuddy/issues
Author-email: Joe Zeitouny <joezeitouny@gmail.com>
License-File: LICENSE
Classifier: License :: OSI Approved :: MIT License
Classifier: Operating System :: OS Independent
Classifier: Programming Language :: Python :: 3
Requires-Python: >=3.7
Requires-Dist: events~=0.4
Requires-Dist: flask~=2.2.3
Requires-Dist: geopy~=2.3.0
Requires-Dist: gpxpy~=1.5.0
Requires-Dist: keyring~=23.13.1
Requires-Dist: latloncalc~=1.5.3
Requires-Dist: mysql-connector-python~=8.0.32
Requires-Dist: numpy~=1.24.1
Requires-Dist: openpyxl~=3.0.10
Requires-Dist: playsound~=1.3.0
Requires-Dist: pymodbustcp~=0.2.0
Requires-Dist: pyobjc~=9.0.1; sys_platform == 'darwin'
Requires-Dist: pyserial
Requires-Dist: rich~=13.3.1
Requires-Dist: yagmail~=0.15.293
